k_fold_imblearn/__init__.py
k_fold_imblearn/helper.py
k_fold_imblearn/k_fold_imblearn.py
k_fold_imblearn-1.0.0.dist-info/LICENSE
k_fold_imblearn-1.0.0.dist-info/METADATA
k_fold_imblearn-1.0.0.dist-info/WHEEL
k_fold_imblearn-1.0.0.dist-info/top_level.txt
k_fold_imblearn-1.0.0.dist-info/RECORD
