Metadata-Version: 2.1
Name: k-fold-imblearn
Version: 1.0.0
Summary: KFoldImblearn handles the resampling of data in a k fold fashion, taking care of information leakage so that our results are not overly optimistic. It is built over the imblearn package and is compatible with all the oversampling as well as under sampling methods provided in the imblearn package.
Home-page: https://github.com/anubhav562/KFoldImblearn
Author: Anubhav Chhabra
Author-email: chhabra.anubhav1997@gmail.com
License: MIT
Platform: UNKNOWN
Classifier: License :: OSI Approved :: MIT License
Classifier: Programming Language :: Python :: 3.6
Classifier: Programming Language :: Python :: 3.7
Classifier: Programming Language :: Python :: 3.8
Requires-Dist: pandas (>=1.1.5)
Requires-Dist: scikit-learn (>=0.24.0)
Requires-Dist: imbalanced-learn (>=0.8.0)
